ai_ml_sdk_scenario_runner-0.8.0.data/purelib/scenario_runner/__init__.py
ai_ml_sdk_scenario_runner-0.8.0.data/purelib/scenario_runner/cli.py
ai_ml_sdk_scenario_runner-0.8.0.data/purelib/scenario_runner/binaries/bin/dds_utils
ai_ml_sdk_scenario_runner-0.8.0.data/purelib/scenario_runner/binaries/bin/glslc
ai_ml_sdk_scenario_runner-0.8.0.data/purelib/scenario_runner/binaries/bin/scenario-runner
ai_ml_sdk_scenario_runner-0.8.0.data/purelib/scenario_runner/binaries/lib/ai-ml-sdk-scenario-runner.spdx.json
ai_ml_sdk_scenario_runner-0.8.0.data/purelib/scenario_runner/binaries/lib/cmake/ScenarioRunner/ScenarioRunnerConfig-debug.cmake
ai_ml_sdk_scenario_runner-0.8.0.data/purelib/scenario_runner/binaries/lib/cmake/ScenarioRunner/ScenarioRunnerConfig-release.cmake
ai_ml_sdk_scenario_runner-0.8.0.data/purelib/scenario_runner/binaries/lib/cmake/ScenarioRunner/ScenarioRunnerConfig.cmake
ai_ml_sdk_scenario_runner-0.8.0.data/purelib/scenario_runner/binaries/lib/cmake/ScenarioRunner/ScenarioRunnerConfigVersion.cmake
ai_ml_sdk_scenario_runner-0.8.0.dist-info/METADATA
ai_ml_sdk_scenario_runner-0.8.0.dist-info/WHEEL
ai_ml_sdk_scenario_runner-0.8.0.dist-info/entry_points.txt
ai_ml_sdk_scenario_runner-0.8.0.dist-info/top_level.txt
ai_ml_sdk_scenario_runner-0.8.0.dist-info/RECORD
