Metadata-Version: 2.4
Name: ai_ml_sdk_scenario_runner
Version: 0.8.0
Summary: ML SDK Scenario Runner
